oas/__init__.py
oas/__version__.py
oas/exceptions.py
oas/spec.py
oas/utils.py
oas/content/__init__.py
oas/content/models.py
oas/content/unmarshalers.py
oas/parameters/__init__.py
oas/parameters/deserializers.py
oas/parameters/models.py
oas/parameters/unmarshalers.py
oas/request/__init__.py
oas/request/models.py
oas/request/unmarshalers.py
oas/request_body/__init__.py
oas/request_body/models.py
oas/request_body/unmarshalers.py
oas/schema/__init__.py
oas/schema/formats.py
oas/schema/unmarshalers.py
oas/schema/validators.py
oas-0.2.0.dist-info/LICENSE.txt
oas-0.2.0.dist-info/METADATA
oas-0.2.0.dist-info/WHEEL
oas-0.2.0.dist-info/top_level.txt
oas-0.2.0.dist-info/RECORD
