Metadata-Version: 2.1
Name: oas
Version: 0.2.0
Summary: Yet another OpenAPI 3 library
Home-page: https://github.com/grktsh/python-oas
License: UNKNOWN
Platform: UNKNOWN
Classifier: Development Status :: 3 - Alpha
Classifier: Intended Audience :: Developers
Classifier: License :: OSI Approved :: Apache Software License
Classifier: Programming Language :: Python :: 2
Classifier: Programming Language :: Python :: 2.7
Classifier: Programming Language :: Python :: 3
Classifier: Programming Language :: Python :: 3.5
Classifier: Programming Language :: Python :: 3.6
Classifier: Programming Language :: Python :: 3.7
Classifier: Programming Language :: Python :: 3.8
Requires-Dist: jsonref (~=0.2)
Requires-Dist: jsonschema (<4,>=2.6)
Requires-Dist: six (~=1.11)
Requires-Dist: functools32 (~=3.2) ; python_version == "2.7"
Provides-Extra: format
Requires-Dist: pyrfc3339 (~=1.1) ; extra == 'format'
Requires-Dist: rfc3986 (~=1.1) ; extra == 'format'
Provides-Extra: test
Requires-Dist: pytest ; extra == 'test'
Requires-Dist: pytest-cov ; extra == 'test'
Requires-Dist: pytest-mock ; extra == 'test'
Requires-Dist: pytest-xdist ; extra == 'test'
Requires-Dist: pyyaml (~=5.1) ; extra == 'test'
